odoo/addons/fleet_vehicle_pivot_graph/README.rst
odoo/addons/fleet_vehicle_pivot_graph/__init__.py
odoo/addons/fleet_vehicle_pivot_graph/__manifest__.py
odoo/addons/fleet_vehicle_pivot_graph/i18n/fleet_vehicle_pivot_graph.pot
odoo/addons/fleet_vehicle_pivot_graph/i18n/it.po
odoo/addons/fleet_vehicle_pivot_graph/i18n/pt_BR.po
odoo/addons/fleet_vehicle_pivot_graph/readme/CONTRIBUTORS.rst
odoo/addons/fleet_vehicle_pivot_graph/readme/CREDITS.rst
odoo/addons/fleet_vehicle_pivot_graph/readme/DESCRIPTION.rst
odoo/addons/fleet_vehicle_pivot_graph/static/description/banner.png
odoo/addons/fleet_vehicle_pivot_graph/static/description/icon.png
odoo/addons/fleet_vehicle_pivot_graph/static/description/index.html
odoo/addons/fleet_vehicle_pivot_graph/views/fleet_vehicle.xml
odoo14_addon_fleet_vehicle_pivot_graph-14.0.1.0.1.dev5.dist-info/METADATA
odoo14_addon_fleet_vehicle_pivot_graph-14.0.1.0.1.dev5.dist-info/WHEEL
odoo14_addon_fleet_vehicle_pivot_graph-14.0.1.0.1.dev5.dist-info/top_level.txt
odoo14_addon_fleet_vehicle_pivot_graph-14.0.1.0.1.dev5.dist-info/RECORD
